staticconfiguration/__init__.py
staticconfiguration/config_base/__init__.py
staticconfiguration/config_base/decorator.py
staticconfiguration/config_base/static_config_base.py
staticconfiguration/config_base/static_config_interface.py
staticconfiguration/entities/__init__.py
staticconfiguration/entities/data.py
staticconfiguration/exceptions/__init__.py
staticconfiguration/exceptions/configuration_reset_warning.py
staticconfiguration/json_backend/__init__.py
staticconfiguration/json_backend/config_payload_migrator.py
staticconfiguration/json_backend/json_backend.py
staticconfiguration-1.0.0.dist-info/licenses/LICENSE
staticconfiguration-1.0.0.dist-info/METADATA
staticconfiguration-1.0.0.dist-info/WHEEL
staticconfiguration-1.0.0.dist-info/top_level.txt
staticconfiguration-1.0.0.dist-info/RECORD
