Metadata-Version: 2.4
Name: staticconfiguration
Version: 1.0.0
Summary: Strongly typed, persistent global configuration for single-machine Python applications.
Author-email: David Muñoz Pecci <davidmpe2002@gmail.com>
License-Expression: MPL-2.0
Project-URL: Homepage, https://github.com/Dmpecci/staticconfiguration
Project-URL: Repository, https://github.com/Dmpecci/staticconfiguration
Project-URL: Issues, https://github.com/Dmpecci/staticconfiguration/issues
Project-URL: Documentation, https://staticconfiguration.readthedocs.io/
Classifier: Development Status :: 5 - Production/Stable
Classifier: Intended Audience :: Developers
Classifier: Operating System :: OS Independent
Classifier: Programming Language :: Python :: 3
Classifier: Programming Language :: Python :: 3.10
Classifier: Programming Language :: Python :: 3.11
Classifier: Programming Language :: Python :: 3.12
Classifier: Topic :: Software Development :: Libraries
Classifier: Topic :: Software Development :: Libraries :: Python Modules
Requires-Python: >=3.10
License-File: LICENSE
Requires-Dist: psutil>=7.1.3
Provides-Extra: dev
Requires-Dist: pytest<10.0.0,>=9.0.2; extra == "dev"
Requires-Dist: pytest-cov<8.0.0,>=7.0.0; extra == "dev"
Dynamic: license-file
